{
  "lastUpdated": "2026-02-21T22:47:56.986Z",
  "keywords": [
    {
      "keyword": "verified",
      "score": 1070,
      "category": "tech",
      "sources": [
        "hackernews"
      ],
      "firstSeen": "2026-02-21T22:47:56.985Z"
    },
    {
      "keyword": "linkedin",
      "score": 1070,
      "category": "tech",
      "sources": [
        "hackernews"
      ],
      "firstSeen": "2026-02-21T22:47:56.985Z"
    },
    {
      "keyword": "identity",
      "score": 1070,
      "category": "tech",
      "sources": [
        "hackernews"
      ],
      "firstSeen": "2026-02-21T22:47:56.985Z"
    },
    {
      "keyword": "handed",
      "score": 1070,
      "category": "tech",
      "sources": [
        "hackernews"
      ],
      "firstSeen": "2026-02-21T22:47:56.985Z"
    },
    {
      "keyword": "write",
      "score": 338,
      "category": "tech",
      "sources": [
        "hackernews"
      ],
      "firstSeen": "2026-02-21T22:47:56.985Z"
    },
    {
      "keyword": "your",
      "score": 338,
      "category": "tech",
      "sources": [
        "hackernews"
      ],
      "firstSeen": "2026-02-21T22:47:56.985Z"
    },
    {
      "keyword": "security",
      "score": 338,
      "category": "tech",
      "sources": [
        "hackernews"
      ],
      "firstSeen": "2026-02-21T22:47:56.985Z"
    },
    {
      "keyword": "clearance",
      "score": 338,
      "category": "tech",
      "sources": [
        "hackernews"
      ],
      "firstSeen": "2026-02-21T22:47:56.985Z"
    },
    {
      "keyword": "form",
      "score": 338,
      "category": "tech",
      "sources": [
        "hackernews"
      ],
      "firstSeen": "2026-02-21T22:47:56.985Z"
    },
    {
      "keyword": "1988",
      "score": 338,
      "category": "tech",
      "sources": [
        "hackernews"
      ],
      "firstSeen": "2026-02-21T22:47:56.985Z"
    },
    {
      "keyword": "back",
      "score": 268,
      "category": "tech",
      "sources": [
        "hackernews"
      ],
      "firstSeen": "2026-02-21T22:47:56.985Z"
    },
    {
      "keyword": "understand",
      "score": 268,
      "category": "tech",
      "sources": [
        "hackernews"
      ],
      "firstSeen": "2026-02-21T22:47:56.985Z"
    },
    {
      "keyword": "english",
      "score": 268,
      "category": "tech",
      "sources": [
        "hackernews"
      ],
      "firstSeen": "2026-02-21T22:47:56.985Z"
    },
    {
      "keyword": "about",
      "score": 167,
      "category": "tech",
      "sources": [
        "hackernews",
        "hackernews"
      ],
      "firstSeen": "2026-02-21T22:47:56.985Z"
    },
    {
      "keyword": "claws",
      "score": 142,
      "category": "tech",
      "sources": [
        "hackernews"
      ],
      "firstSeen": "2026-02-21T22:47:56.985Z"
    },
    {
      "keyword": "layer",
      "score": 142,
      "category": "tech",
      "sources": [
        "hackernews"
      ],
      "firstSeen": "2026-02-21T22:47:56.985Z"
    },
    {
      "keyword": "agents",
      "score": 142,
      "category": "tech",
      "sources": [
        "hackernews"
      ],
      "firstSeen": "2026-02-21T22:47:56.985Z"
    },
    {
      "keyword": "personal",
      "score": 139,
      "category": "tech",
      "sources": [
        "hackernews",
        "hackernews"
      ],
      "firstSeen": "2026-02-21T22:47:56.985Z"
    },
    {
      "keyword": "cloudflare",
      "score": 123,
      "category": "tech",
      "sources": [
        "hackernews"
      ],
      "firstSeen": "2026-02-21T22:47:56.985Z"
    },
    {
      "keyword": "outage",
      "score": 123,
      "category": "tech",
      "sources": [
        "hackernews"
      ],
      "firstSeen": "2026-02-21T22:47:56.985Z"
    },
    {
      "keyword": "february",
      "score": 123,
      "category": "tech",
      "sources": [
        "hackernews"
      ],
      "firstSeen": "2026-02-21T22:47:56.985Z"
    },
    {
      "keyword": "2026",
      "score": 123,
      "category": "tech",
      "sources": [
        "hackernews"
      ],
      "firstSeen": "2026-02-21T22:47:56.985Z"
    },
    {
      "keyword": "cxmt",
      "score": 121,
      "category": "tech",
      "sources": [
        "hackernews"
      ],
      "firstSeen": "2026-02-21T22:47:56.985Z"
    },
    {
      "keyword": "offering",
      "score": 121,
      "category": "tech",
      "sources": [
        "hackernews"
      ],
      "firstSeen": "2026-02-21T22:47:56.985Z"
    },
    {
      "keyword": "ddr4",
      "score": 121,
      "category": "tech",
      "sources": [
        "hackernews"
      ],
      "firstSeen": "2026-02-21T22:47:56.985Z"
    },
    {
      "keyword": "chips",
      "score": 121,
      "category": "tech",
      "sources": [
        "hackernews"
      ],
      "firstSeen": "2026-02-21T22:47:56.985Z"
    },
    {
      "keyword": "half",
      "score": 121,
      "category": "tech",
      "sources": [
        "hackernews"
      ],
      "firstSeen": "2026-02-21T22:47:56.985Z"
    },
    {
      "keyword": "prevailing",
      "score": 121,
      "category": "tech",
      "sources": [
        "hackernews"
      ],
      "firstSeen": "2026-02-21T22:47:56.985Z"
    },
    {
      "keyword": "market",
      "score": 121,
      "category": "tech",
      "sources": [
        "hackernews"
      ],
      "firstSeen": "2026-02-21T22:47:56.985Z"
    },
    {
      "keyword": "rate",
      "score": 121,
      "category": "tech",
      "sources": [
        "hackernews"
      ],
      "firstSeen": "2026-02-21T22:47:56.985Z"
    },
    {
      "keyword": "statement",
      "score": 100,
      "category": "tech",
      "sources": [
        "hackernews"
      ],
      "firstSeen": "2026-02-21T22:47:56.985Z"
    },
    {
      "keyword": "analyst",
      "score": 100,
      "category": "tech",
      "sources": [
        "hackernews"
      ],
      "firstSeen": "2026-02-21T22:47:56.985Z"
    },
    {
      "keyword": "eduke32",
      "score": 98,
      "category": "tech",
      "sources": [
        "hackernews"
      ],
      "firstSeen": "2026-02-21T22:47:56.985Z"
    },
    {
      "keyword": "duke",
      "score": 98,
      "category": "tech",
      "sources": [
        "hackernews"
      ],
      "firstSeen": "2026-02-21T22:47:56.985Z"
    },
    {
      "keyword": "nukem",
      "score": 98,
      "category": "tech",
      "sources": [
        "hackernews"
      ],
      "firstSeen": "2026-02-21T22:47:56.985Z"
    },
    {
      "keyword": "open",
      "score": 98,
      "category": "tech",
      "sources": [
        "hackernews"
      ],
      "firstSeen": "2026-02-21T22:47:56.985Z"
    },
    {
      "keyword": "source",
      "score": 98,
      "category": "tech",
      "sources": [
        "hackernews"
      ],
      "firstSeen": "2026-02-21T22:47:56.985Z"
    },
    {
      "keyword": "React",
      "score": 92,
      "category": "development",
      "sources": [
        "github-trending"
      ],
      "firstSeen": "2026-02-21T22:47:56.985Z"
    },
    {
      "keyword": "TypeScript",
      "score": 91,
      "category": "development",
      "sources": [
        "github-trending"
      ],
      "firstSeen": "2026-02-21T22:47:56.985Z"
    },
    {
      "keyword": "AI",
      "score": 90,
      "category": "development",
      "sources": [
        "github-trending"
      ],
      "firstSeen": "2026-02-21T22:47:56.985Z"
    },
    {
      "keyword": "Blockchain",
      "score": 89,
      "category": "development",
      "sources": [
        "github-trending"
      ],
      "firstSeen": "2026-02-21T22:47:56.985Z"
    },
    {
      "keyword": "parse",
      "score": 86,
      "category": "tech",
      "sources": [
        "hackernews"
      ],
      "firstSeen": "2026-02-21T22:47:56.985Z"
    },
    {
      "keyword": "validate",
      "score": 86,
      "category": "tech",
      "sources": [
        "hackernews"
      ],
      "firstSeen": "2026-02-21T22:47:56.985Z"
    },
    {
      "keyword": "type",
      "score": 86,
      "category": "tech",
      "sources": [
        "hackernews"
      ],
      "firstSeen": "2026-02-21T22:47:56.985Z"
    },
    {
      "keyword": "driven",
      "score": 86,
      "category": "tech",
      "sources": [
        "hackernews"
      ],
      "firstSeen": "2026-02-21T22:47:56.985Z"
    },
    {
      "keyword": "design",
      "score": 86,
      "category": "tech",
      "sources": [
        "hackernews"
      ],
      "firstSeen": "2026-02-21T22:47:56.985Z"
    },
    {
      "keyword": "rust",
      "score": 86,
      "category": "tech",
      "sources": [
        "hackernews"
      ],
      "firstSeen": "2026-02-21T22:47:56.985Z"
    },
    {
      "keyword": "magic",
      "score": 73,
      "category": "tech",
      "sources": [
        "hackernews"
      ],
      "firstSeen": "2026-02-21T22:47:56.985Z"
    },
    {
      "keyword": "Machine Learning",
      "score": 68,
      "category": "development",
      "sources": [
        "github-trending"
      ],
      "firstSeen": "2026-02-21T22:47:56.985Z"
    },
    {
      "keyword": "JavaScript",
      "score": 64,
      "category": "development",
      "sources": [
        "github-trending"
      ],
      "firstSeen": "2026-02-21T22:47:56.985Z"
    }
  ]
}