{
  "lastUpdated": "2025-08-04T20:17:30.225Z",
  "keywords": [
    {
      "keyword": "perplexity",
      "score": 780,
      "category": "tech",
      "sources": [
        "hackernews"
      ],
      "firstSeen": "2025-08-04T20:17:30.224Z"
    },
    {
      "keyword": "using",
      "score": 780,
      "category": "tech",
      "sources": [
        "hackernews"
      ],
      "firstSeen": "2025-08-04T20:17:30.224Z"
    },
    {
      "keyword": "stealth",
      "score": 780,
      "category": "tech",
      "sources": [
        "hackernews"
      ],
      "firstSeen": "2025-08-04T20:17:30.224Z"
    },
    {
      "keyword": "undeclared",
      "score": 780,
      "category": "tech",
      "sources": [
        "hackernews"
      ],
      "firstSeen": "2025-08-04T20:17:30.224Z"
    },
    {
      "keyword": "crawlers",
      "score": 780,
      "category": "tech",
      "sources": [
        "hackernews"
      ],
      "firstSeen": "2025-08-04T20:17:30.224Z"
    },
    {
      "keyword": "evade",
      "score": 780,
      "category": "tech",
      "sources": [
        "hackernews"
      ],
      "firstSeen": "2025-08-04T20:17:30.224Z"
    },
    {
      "keyword": "crawl",
      "score": 780,
      "category": "tech",
      "sources": [
        "hackernews"
      ],
      "firstSeen": "2025-08-04T20:17:30.224Z"
    },
    {
      "keyword": "directives",
      "score": 780,
      "category": "tech",
      "sources": [
        "hackernews"
      ],
      "firstSeen": "2025-08-04T20:17:30.224Z"
    },
    {
      "keyword": "show",
      "score": 444,
      "category": "tech",
      "sources": [
        "hackernews",
        "hackernews"
      ],
      "firstSeen": "2025-08-04T20:17:30.224Z"
    },
    {
      "keyword": "spent",
      "score": 409,
      "category": "tech",
      "sources": [
        "hackernews"
      ],
      "firstSeen": "2025-08-04T20:17:30.224Z"
    },
    {
      "keyword": "years",
      "score": 409,
      "category": "tech",
      "sources": [
        "hackernews"
      ],
      "firstSeen": "2025-08-04T20:17:30.224Z"
    },
    {
      "keyword": "building",
      "score": 409,
      "category": "tech",
      "sources": [
        "hackernews"
      ],
      "firstSeen": "2025-08-04T20:17:30.224Z"
    },
    {
      "keyword": "ridiculous",
      "score": 409,
      "category": "tech",
      "sources": [
        "hackernews"
      ],
      "firstSeen": "2025-08-04T20:17:30.224Z"
    },
    {
      "keyword": "wooden",
      "score": 409,
      "category": "tech",
      "sources": [
        "hackernews"
      ],
      "firstSeen": "2025-08-04T20:17:30.224Z"
    },
    {
      "keyword": "pixel",
      "score": 409,
      "category": "tech",
      "sources": [
        "hackernews"
      ],
      "firstSeen": "2025-08-04T20:17:30.224Z"
    },
    {
      "keyword": "display",
      "score": 409,
      "category": "tech",
      "sources": [
        "hackernews"
      ],
      "firstSeen": "2025-08-04T20:17:30.224Z"
    },
    {
      "keyword": "seekers",
      "score": 377,
      "category": "tech",
      "sources": [
        "hackernews"
      ],
      "firstSeen": "2025-08-04T20:17:30.224Z"
    },
    {
      "keyword": "dodging",
      "score": 377,
      "category": "tech",
      "sources": [
        "hackernews"
      ],
      "firstSeen": "2025-08-04T20:17:30.224Z"
    },
    {
      "keyword": "interviewers",
      "score": 377,
      "category": "tech",
      "sources": [
        "hackernews"
      ],
      "firstSeen": "2025-08-04T20:17:30.224Z"
    },
    {
      "keyword": "built",
      "score": 243,
      "category": "tech",
      "sources": [
        "hackernews"
      ],
      "firstSeen": "2025-08-04T20:17:30.224Z"
    },
    {
      "keyword": "bluey",
      "score": 243,
      "category": "tech",
      "sources": [
        "hackernews"
      ],
      "firstSeen": "2025-08-04T20:17:30.224Z"
    },
    {
      "keyword": "world",
      "score": 243,
      "category": "tech",
      "sources": [
        "hackernews"
      ],
      "firstSeen": "2025-08-04T20:17:30.224Z"
    },
    {
      "keyword": "openipc",
      "score": 145,
      "category": "tech",
      "sources": [
        "hackernews"
      ],
      "firstSeen": "2025-08-04T20:17:30.224Z"
    },
    {
      "keyword": "open",
      "score": 145,
      "category": "tech",
      "sources": [
        "hackernews"
      ],
      "firstSeen": "2025-08-04T20:17:30.224Z"
    },
    {
      "keyword": "camera",
      "score": 145,
      "category": "tech",
      "sources": [
        "hackernews"
      ],
      "firstSeen": "2025-08-04T20:17:30.224Z"
    },
    {
      "keyword": "firmware",
      "score": 145,
      "category": "tech",
      "sources": [
        "hackernews"
      ],
      "firstSeen": "2025-08-04T20:17:30.224Z"
    },
    {
      "keyword": "stone",
      "score": 142,
      "category": "tech",
      "sources": [
        "hackernews",
        "hackernews"
      ],
      "firstSeen": "2025-08-04T20:17:30.224Z"
    },
    {
      "keyword": "drawafish",
      "score": 140,
      "category": "tech",
      "sources": [
        "hackernews"
      ],
      "firstSeen": "2025-08-04T20:17:30.224Z"
    },
    {
      "keyword": "postmortem",
      "score": 140,
      "category": "tech",
      "sources": [
        "hackernews"
      ],
      "firstSeen": "2025-08-04T20:17:30.224Z"
    },
    {
      "keyword": "deep",
      "score": 108,
      "category": "tech",
      "sources": [
        "hackernews"
      ],
      "firstSeen": "2025-08-04T20:17:30.224Z"
    },
    {
      "keyword": "dive",
      "score": 108,
      "category": "tech",
      "sources": [
        "hackernews"
      ],
      "firstSeen": "2025-08-04T20:17:30.224Z"
    },
    {
      "keyword": "into",
      "score": 108,
      "category": "tech",
      "sources": [
        "hackernews"
      ],
      "firstSeen": "2025-08-04T20:17:30.224Z"
    },
    {
      "keyword": "rust",
      "score": 108,
      "category": "tech",
      "sources": [
        "hackernews"
      ],
      "firstSeen": "2025-08-04T20:17:30.224Z"
    },
    {
      "keyword": "memory",
      "score": 108,
      "category": "tech",
      "sources": [
        "hackernews"
      ],
      "firstSeen": "2025-08-04T20:17:30.224Z"
    },
    {
      "keyword": "interoperability",
      "score": 108,
      "category": "tech",
      "sources": [
        "hackernews"
      ],
      "firstSeen": "2025-08-04T20:17:30.224Z"
    },
    {
      "keyword": "century",
      "score": 108,
      "category": "tech",
      "sources": [
        "hackernews"
      ],
      "firstSeen": "2025-08-04T20:17:30.224Z"
    },
    {
      "keyword": "tsunami",
      "score": 108,
      "category": "tech",
      "sources": [
        "hackernews"
      ],
      "firstSeen": "2025-08-04T20:17:30.224Z"
    },
    {
      "keyword": "stones",
      "score": 108,
      "category": "tech",
      "sources": [
        "hackernews"
      ],
      "firstSeen": "2025-08-04T20:17:30.224Z"
    },
    {
      "keyword": "japan",
      "score": 108,
      "category": "tech",
      "sources": [
        "hackernews"
      ],
      "firstSeen": "2025-08-04T20:17:30.224Z"
    },
    {
      "keyword": "coastline",
      "score": 108,
      "category": "tech",
      "sources": [
        "hackernews"
      ],
      "firstSeen": "2025-08-04T20:17:30.224Z"
    },
    {
      "keyword": "2015",
      "score": 108,
      "category": "tech",
      "sources": [
        "hackernews"
      ],
      "firstSeen": "2025-08-04T20:17:30.224Z"
    },
    {
      "keyword": "ideal",
      "score": 95,
      "category": "tech",
      "sources": [
        "hackernews"
      ],
      "firstSeen": "2025-08-04T20:17:30.224Z"
    },
    {
      "keyword": "array",
      "score": 95,
      "category": "tech",
      "sources": [
        "hackernews"
      ],
      "firstSeen": "2025-08-04T20:17:30.224Z"
    },
    {
      "keyword": "language",
      "score": 95,
      "category": "tech",
      "sources": [
        "hackernews"
      ],
      "firstSeen": "2025-08-04T20:17:30.224Z"
    },
    {
      "keyword": "TypeScript",
      "score": 95,
      "category": "development",
      "sources": [
        "github-trending"
      ],
      "firstSeen": "2025-08-04T20:17:30.224Z"
    },
    {
      "keyword": "Database",
      "score": 95,
      "category": "development",
      "sources": [
        "github-trending"
      ],
      "firstSeen": "2025-08-04T20:17:30.224Z"
    },
    {
      "keyword": "React",
      "score": 92,
      "category": "development",
      "sources": [
        "github-trending"
      ],
      "firstSeen": "2025-08-04T20:17:30.224Z"
    },
    {
      "keyword": "Angular",
      "score": 91,
      "category": "development",
      "sources": [
        "github-trending"
      ],
      "firstSeen": "2025-08-04T20:17:30.224Z"
    },
    {
      "keyword": "Kubernetes",
      "score": 90,
      "category": "development",
      "sources": [
        "github-trending"
      ],
      "firstSeen": "2025-08-04T20:17:30.224Z"
    },
    {
      "keyword": "Machine Learning",
      "score": 90,
      "category": "development",
      "sources": [
        "github-trending"
      ],
      "firstSeen": "2025-08-04T20:17:30.224Z"
    }
  ]
}